awslabs/__init__.py
awslabs/aws_dataprocessing_mcp_server/__init__.py
awslabs/aws_dataprocessing_mcp_server/server.py
awslabs/aws_dataprocessing_mcp_server/core/__init__.py
awslabs/aws_dataprocessing_mcp_server/core/glue_data_catalog/__init__.py
awslabs/aws_dataprocessing_mcp_server/core/glue_data_catalog/data_catalog_database_manager.py
awslabs/aws_dataprocessing_mcp_server/core/glue_data_catalog/data_catalog_handler.py
awslabs/aws_dataprocessing_mcp_server/core/glue_data_catalog/data_catalog_table_manager.py
awslabs/aws_dataprocessing_mcp_server/handlers/__init__.py
awslabs/aws_dataprocessing_mcp_server/handlers/athena/__init__.py
awslabs/aws_dataprocessing_mcp_server/handlers/athena/athena_data_catalog_handler.py
awslabs/aws_dataprocessing_mcp_server/handlers/athena/athena_query_handler.py
awslabs/aws_dataprocessing_mcp_server/handlers/athena/athena_workgroup_handler.py
awslabs/aws_dataprocessing_mcp_server/handlers/commons/__init__.py
awslabs/aws_dataprocessing_mcp_server/handlers/commons/common_resource_handler.py
awslabs/aws_dataprocessing_mcp_server/handlers/emr/emr_ec2_cluster_handler.py
awslabs/aws_dataprocessing_mcp_server/handlers/emr/emr_ec2_instance_handler.py
awslabs/aws_dataprocessing_mcp_server/handlers/emr/emr_ec2_steps_handler.py
awslabs/aws_dataprocessing_mcp_server/handlers/emr/emr_serverless_application_handler.py
awslabs/aws_dataprocessing_mcp_server/handlers/emr/emr_serverless_job_run_handler.py
awslabs/aws_dataprocessing_mcp_server/handlers/glue/__init__.py
awslabs/aws_dataprocessing_mcp_server/handlers/glue/crawler_handler.py
awslabs/aws_dataprocessing_mcp_server/handlers/glue/data_catalog_handler.py
awslabs/aws_dataprocessing_mcp_server/handlers/glue/glue_commons_handler.py
awslabs/aws_dataprocessing_mcp_server/handlers/glue/glue_etl_handler.py
awslabs/aws_dataprocessing_mcp_server/handlers/glue/interactive_sessions_handler.py
awslabs/aws_dataprocessing_mcp_server/handlers/glue/worklows_handler.py
awslabs_aws_dataprocessing_mcp_server-0.1.20.dist-info/METADATA
awslabs_aws_dataprocessing_mcp_server-0.1.20.dist-info/WHEEL
awslabs_aws_dataprocessing_mcp_server-0.1.20.dist-info/entry_points.txt
awslabs_aws_dataprocessing_mcp_server-0.1.20.dist-info/licenses/LICENSE
awslabs_aws_dataprocessing_mcp_server-0.1.20.dist-info/licenses/NOTICE
awslabs_aws_dataprocessing_mcp_server-0.1.20.dist-info/RECORD
